[
  {
    "No": "1",
    "Name": "Basic Materials",
    "Perf_Week": "0.99%",
    "Perf_Month": "5.67%",
    "Perf_Quart": "12.90%",
    "Perf_Half": "16.85%",
    "Perf_Year": "16.19%",
    "Perf_YTD": "23.90%",
    "Recom": "2.05",
    "Avg_Volume": "695.52M",
    "Rel_Volume": "1.03",
    "Change": "0.39%",
    "Volume": "717.66M"
  },
  {
    "No": "2",
    "Name": "Communication Services",
    "Perf_Week": "3.41%",
    "Perf_Month": "8.87%",
    "Perf_Quart": "20.42%",
    "Perf_Half": "31.53%",
    "Perf_Year": "50.32%",
    "Perf_YTD": "27.89%",
    "Recom": "1.62",
    "Avg_Volume": "676.23M",
    "Rel_Volume": "1.19",
    "Change": "2.08%",
    "Volume": "805.38M"
  },
  {
    "No": "3",
    "Name": "Consumer Cyclical",
    "Perf_Week": "1.65%",
    "Perf_Month": "5.18%",
    "Perf_Quart": "13.76%",
    "Perf_Half": "19.94%",
    "Perf_Year": "26.81%",
    "Perf_YTD": "8.49%",
    "Recom": "1.84",
    "Avg_Volume": "1.36B",
    "Rel_Volume": "1.00",
    "Change": "0.99%",
    "Volume": "1.35B"
  },
  {
    "No": "4",
    "Name": "Consumer Defensive",
    "Perf_Week": "-0.89%",
    "Perf_Month": "-1.54%",
    "Perf_Quart": "-0.67%",
    "Perf_Half": "3.85%",
    "Perf_Year": "2.20%",
    "Perf_YTD": "5.14%",
    "Recom": "1.94",
    "Avg_Volume": "507.41M",
    "Rel_Volume": "1.00",
    "Change": "-0.95%",
    "Volume": "508.93M"
  },
  {
    "No": "5",
    "Name": "Energy",
    "Perf_Week": "1.58%",
    "Perf_Month": "2.36%",
    "Perf_Quart": "0.19%",
    "Perf_Half": "1.69%",
    "Perf_Year": "6.67%",
    "Perf_YTD": "4.64%",
    "Recom": "1.96",
    "Avg_Volume": "691.54M",
    "Rel_Volume": "1.07",
    "Change": "0.23%",
    "Volume": "737.31M"
  },
  {
    "No": "6",
    "Name": "Financial",
    "Perf_Week": "1.24%",
    "Perf_Month": "1.78%",
    "Perf_Quart": "9.45%",
    "Perf_Half": "14.42%",
    "Perf_Year": "26.18%",
    "Perf_YTD": "16.28%",
    "Recom": "2.06",
    "Avg_Volume": "1.51B",
    "Rel_Volume": "1.07",
    "Change": "-0.01%",
    "Volume": "1.61B"
  },
  {
    "No": "7",
    "Name": "Healthcare",
    "Perf_Week": "-1.17%",
    "Perf_Month": "1.70%",
    "Perf_Quart": "0.43%",
    "Perf_Half": "-5.03%",
    "Perf_Year": "-11.85%",
    "Perf_YTD": "-1.47%",
    "Recom": "1.87",
    "Avg_Volume": "1.55B",
    "Rel_Volume": "1.17",
    "Change": "-0.93%",
    "Volume": "1.81B"
  },
  {
    "No": "8",
    "Name": "Industrials",
    "Perf_Week": "0.53%",
    "Perf_Month": "0.63%",
    "Perf_Quart": "7.27%",
    "Perf_Half": "16.91%",
    "Perf_Year": "18.24%",
    "Perf_YTD": "13.64%",
    "Recom": "2.01",
    "Avg_Volume": "979.98M",
    "Rel_Volume": "1.04",
    "Change": "0.43%",
    "Volume": "1.02B"
  },
  {
    "No": "9",
    "Name": "Real Estate",
    "Perf_Week": "0.56%",
    "Perf_Month": "3.70%",
    "Perf_Quart": "3.49%",
    "Perf_Half": "2.35%",
    "Perf_Year": "-4.39%",
    "Perf_YTD": "3.64%",
    "Recom": "1.92",
    "Avg_Volume": "685.26M",
    "Rel_Volume": "1.11",
    "Change": "-0.33%",
    "Volume": "763.06M"
  },
  {
    "No": "10",
    "Name": "Technology",
    "Perf_Week": "3.50%",
    "Perf_Month": "2.97%",
    "Perf_Quart": "16.09%",
    "Perf_Half": "29.70%",
    "Perf_Year": "30.18%",
    "Perf_YTD": "18.40%",
    "Recom": "1.67",
    "Avg_Volume": "2.50B",
    "Rel_Volume": "1.02",
    "Change": "0.96%",
    "Volume": "2.54B"
  },
  {
    "No": "11",
    "Name": "Utilities",
    "Perf_Week": "3.42%",
    "Perf_Month": "-0.10%",
    "Perf_Quart": "5.49%",
    "Perf_Half": "10.10%",
    "Perf_Year": "12.04%",
    "Perf_YTD": "14.21%",
    "Recom": "2.18",
    "Avg_Volume": "216.44M",
    "Rel_Volume": "0.93",
    "Change": "0.31%",
    "Volume": "200.72M"
  }
]